{
    "multiple" : {
        "title":"UPS Terminology (Multiple)",
        "slides":[
            {
                "heading": "Destination Scan",
                "copy": "A destination scan shows that the shipment has arrived at the local UPS facility responsible for final delivery.",
                "link":"#glossary"
            },
            {
                "heading": "Destination Scan",
                "copy": "A destination scan shows that the shipment has arrived at the local UPS facility responsible for final delivery.",
                "link":"#glossary"
            },
            {
                "heading": "Destination Scan",
                "copy": "A destination scan shows that the shipment has arrived at the local UPS facility responsible for final delivery.",
                "link":"#glossary"
            }
        ]
    },
    "one" : {
        "title":"UPS Terminology (Single)",
        "slides":[{
            "heading": "Destination Scan",
            "copy": "A destination scan shows that the shipment has arrived at the local UPS facility responsible for final delivery.",
            "link":"#glossary"
        }]
    }
}
