{
		"error" : "true", 
		"error_option" : [
			{"link" : "email", "field_name" : "Email or User Id"},
			{"link" : "password", "field_name" : "Password"}
		],
		"signup" : "true",
		"social_option" : [
			{"class" : "facebook", "name" : "Facebook"},
			{"class" : "linkedin", "name" : "LinkedIn"},
			{"class" : "google", "name" : "Google+"},
			{"class" : "amazon", "name" : "Amazon"}
		],
		"socials" : "true",
		"req_fields" : "true",
		"non_social" : "true",
		"form" : "true",
		"form_content" : "true",
		"email_copy" : "Email or User Id",
		"email" : "true",
		"password" : "true",
		"agreement_checkbox" : "true",
		"email_checkbox" : "true",
		"tech_agreement" : "true",
		"captcha" : "true",
		"button" : [
			{"button_type" : "button", "button_class" : "primary", "button_copy" : "Log In"}
		]
}